bbpp/__init__.py
bbpp/main.py
bbpp/assets/audio/cars.wav
bbpp/assets/audio/goat.wav
bbpp/assets/audio/ping.wav
bbpp/modules/__init__.py
bbpp/modules/service/__init__.py
bbpp/modules/service/argparser.py
bbpp/modules/service/bitbucket.py
bbpp/modules/service/config.py
tests/__init__.py
tests/test_args.py
tests/test_bitbucket.py
tests/test_config.py
bbpp-0.0.4.dist-info/LICENSE
bbpp-0.0.4.dist-info/METADATA
bbpp-0.0.4.dist-info/WHEEL
bbpp-0.0.4.dist-info/entry_points.txt
bbpp-0.0.4.dist-info/top_level.txt
bbpp-0.0.4.dist-info/RECORD
