Metadata-Version: 2.1
Name: bbpp
Version: 0.0.4
Summary: Monitor bitbucket pipelines and notify on any status change
Home-page: https://www.github.com/sergiopena/bbpp
Author: Sergio Pena
Author-email: isergiopena@gmail.com
License: BSD
Keywords: bitbucket monitor macos notify
Classifier: Development Status :: 3 - Alpha
Classifier: Topic :: Utilities
Classifier: License :: OSI Approved :: BSD License
License-File: LICENSE
Requires-Dist: httpx ==0.24.1
Requires-Dist: notify-py ==0.3.42
